[{"line":1,"elements":[{"start_timestamp":"2022-07-18T04:03:45.352Z","before":[{"result":{"duration":2747266400,"status":"passed"},"match":{"location":"StepDefinitions.Hooks.setUpScenario()"}}],"line":3,"name":"Testing Websturant functionality and Verification.","description":"","id":"websturant-search-functionality-and-verification;testing-websturant-functionality-and-verification.","after":[{"result":{"duration":228726600,"status":"passed"},"match":{"location":"StepDefinitions.Hooks.tearDownScenario(io.cucumber.java.Scenario)"}}],"type":"scenario","keyword":"Scenario","steps":[{"result":{"duration":822917100,"status":"passed"},"line":4,"name":"User in on Websturant home Page","match":{"location":"StepDefinitions.SearchTable_stepDefinitions.user_in_on_websturant_home_page()"},"keyword":"Given "},{"result":{"duration":1580353400,"status":"passed"},"line":5,"name":"User search for 'stainless work table' in the Websturant search box and enter","match":{"arguments":[{"val":"'stainless work table'","offset":16}],"location":"StepDefinitions.SearchTable_stepDefinitions.user_search_for_in_the_websturant_search_box_and_enter(java.lang.String)"},"keyword":"When "},{"result":{"duration":859069700,"status":"passed"},"line":6,"name":"Ensuring every product item has the word \"Table\" its title.","match":{"arguments":[{"val":"\"Table\"","offset":41}],"location":"StepDefinitions.SearchTable_stepDefinitions.ensuring_every_product_item_has_the_word_its_title(java.lang.String)"},"keyword":"Then "},{"result":{"duration":3308186100,"status":"passed"},"line":7,"name":"User add the last item found to Cart.","match":{"location":"StepDefinitions.SearchTable_stepDefinitions.user_add_the_last_item_found_to_cart()"},"keyword":"Then "},{"result":{"duration":1067095100,"status":"passed"},"line":8,"name":"User Empty the Cart.","match":{"location":"StepDefinitions.SearchTable_stepDefinitions.empty_the_cart()"},"keyword":"And "}]}],"name":"Websturant search functionality and verification","description":"","id":"websturant-search-functionality-and-verification","keyword":"Feature","uri":"file:src/test/resources/features/ResultResult.feature","tags":[]}]